odoo/addons/sale_timesheet_budget/README.rst
odoo/addons/sale_timesheet_budget/__init__.py
odoo/addons/sale_timesheet_budget/__manifest__.py
odoo/addons/sale_timesheet_budget/i18n/es.po
odoo/addons/sale_timesheet_budget/i18n/it.po
odoo/addons/sale_timesheet_budget/i18n/pt_BR.po
odoo/addons/sale_timesheet_budget/i18n/sale_timesheet_budget.pot
odoo/addons/sale_timesheet_budget/models/__init__.py
odoo/addons/sale_timesheet_budget/models/project_project.py
odoo/addons/sale_timesheet_budget/readme/CONTRIBUTORS.rst
odoo/addons/sale_timesheet_budget/readme/DESCRIPTION.rst
odoo/addons/sale_timesheet_budget/readme/ROADMAP.rst
odoo/addons/sale_timesheet_budget/readme/USAGE.rst
odoo/addons/sale_timesheet_budget/security/ir.model.access.csv
odoo/addons/sale_timesheet_budget/static/description/icon.png
odoo/addons/sale_timesheet_budget/static/description/index.html
odoo/addons/sale_timesheet_budget/tests/__init__.py
odoo/addons/sale_timesheet_budget/tests/test_sale_timesheet_budget.py
odoo/addons/sale_timesheet_budget/views/project_project_view.xml
odoo_addon_sale_timesheet_budget-16.0.1.0.0.5.dist-info/METADATA
odoo_addon_sale_timesheet_budget-16.0.1.0.0.5.dist-info/WHEEL
odoo_addon_sale_timesheet_budget-16.0.1.0.0.5.dist-info/top_level.txt
odoo_addon_sale_timesheet_budget-16.0.1.0.0.5.dist-info/RECORD
